sdu_bkjws/__init__.py
sdu_bkjws-1.1.0.dist-info/DESCRIPTION.rst
sdu_bkjws-1.1.0.dist-info/METADATA
sdu_bkjws-1.1.0.dist-info/RECORD
sdu_bkjws-1.1.0.dist-info/WHEEL
sdu_bkjws-1.1.0.dist-info/metadata.json
sdu_bkjws-1.1.0.dist-info/top_level.txt
sdu_bkjws-1.1.0.dist-info/zip-safe
