Metadata-Version: 2.0
Name: sdu-bkjws
Version: 1.1.0
Summary: sdu bkjws library
Home-page: https://github.com/Trim21/sdu_bkjws
Author: Trim21
Author-email: trim21me@gmail.com
License: GPLv3
Platform: any
Classifier: Programming Language :: Python
Classifier: Programming Language :: Python :: 3
Classifier: Programming Language :: Python :: 3.5
Classifier: Programming Language :: Python :: 3.6
Classifier: Programming Language :: Python :: Implementation :: CPython
Classifier: Programming Language :: Python :: Implementation :: PyPy
Requires-Dist: beautifulsoup4 (>4)
Requires-Dist: requests (>2)
